fleaux/__init__.py
fleaux/__main__.py
fleaux-1.0.0.dist-info/LICENSE
fleaux-1.0.0.dist-info/METADATA
fleaux-1.0.0.dist-info/WHEEL
fleaux-1.0.0.dist-info/entry_points.txt
fleaux-1.0.0.dist-info/top_level.txt
fleaux-1.0.0.dist-info/RECORD
