Metadata-Version: 2.1
Name: fleaux
Version: 1.0.0
Summary: setup up boilerplate code for python and c++
Home-page: UNKNOWN
Author: Oliver G.
Author-email: oliverbcontact@gmail.com
License: GNU
Platform: UNKNOWN
Classifier: Programming Language :: Python :: 3.9
Requires-Dist: libog
